py_i18n_countries/__init__.py
py_i18n_countries/countries.py
py_i18n_countries/en.json
py_i18n_countries-0.1.1.dist-info/LICENSE
py_i18n_countries-0.1.1.dist-info/METADATA
py_i18n_countries-0.1.1.dist-info/WHEEL
py_i18n_countries-0.1.1.dist-info/top_level.txt
py_i18n_countries-0.1.1.dist-info/RECORD
